{
  "app_name": "Hello World!",
  "invalid_route": "અમાન્ય રૂટ",
  "share_target_title": "ઉદાહરણ શેર કરો",
  "custom_sdk_app_contact_type": "SDK નમૂનો",
  "contact_subtitle": "કસ્ટમ SDK સંપર્ક",
  "contact_group_1": "સમૂહ 1: મુળ વતન પ્રતિક્રિયામાંથી સંપર્કો",
  "contact_group_2": "સમૂહ 2: મુળ વતન પ્રતિક્રિયામાંથી સંપર્કો",
  "contact_section_phone": "ફોન",
  "contact_section_website": "વેબસાઇટ",
  "contact_section_personal_info": "વ્યક્તિગત માહિતી",
  "contact_section_greetings": "અભિવાદન",
  "contact_greeting": "આપનું સ્વાગત છે!",
  "contact_section_notes": "નોટ્સ",
  "contact_note_1": "નોટ 1",
  "contact_note_2": "MSN",
  "contact_note_3": "ઉદાહરણ એપ્લિકેશન ખોલો",
  "hello_world_view_title": "હોમ",
  "hello_world_view_title_updated": "હોમ (અપડેટ કરેલ)",
  "greeting_view_title": "અભિવાદન",
  "menu_item_1_title": "મેનૂ આઇટમ 1",
  "menu_item_2_title": "મેનૂ આઇટમ 2",
  "menu_item_selected": "તમે આ id વાળી મેનૂ આઇટમ પસંદ કરી: ",
  "snackbar_dismiss_btn": "કાઢી નાંખો",
  "greeting_close_btn": "મૉડ્યૂલ બંધ કરો",
  "greeting_close_btn_with_result": "પરિણામ સાથે મૉડ્યૂલ બંધ કરો",
  "greeting_update_contact_btn": "સંપર્ક અપડેટ કરો",
  "greeting_update_contact_editing": "સંપાદન કરી રહ્યાં છીએ ",
  "greeting_update_contact_edited_name": " (સંપાદિત કરેલ)",
  "greeting_update_contact_edited_desc": "હું એક અપડેટ કરેલ સંપર્ક છું.",
  "greeting_subTitle": "ઉપશીર્ષક - ડ્રૉપડાઉન",
  "auth_view_title": "પ્રમાણીકરણ",
  "get_graph_access_token_btn_title": "ગ્રાફ ઍક્સેસ ટોકન મેળવો",
  "get_graph_access_token_btn_accessibility_label": "ગ્રાફ ઍક્સેસ ટોકન બટન મેળવો",
  "get_graph_access_token_success_message": "ગ્રાફ API માટે ઍક્સેસ ટોકન મળ્યું.",
  "get_graph_access_token_failure_message": "ગ્રાફ API માટે ઍક્સેસ ટોકન મેળવવામાં નિષ્ફળ.",
  "get_skype_token_btn_title": "Skype ટોકન મેળવો",
  "get_skype_token_btn_accessibility_label": "Skype ટોકન બટન મેળવો",
  "get_skype_token_success_message": "ગ્રાફ API માટે skype ટોકન મળ્યું.",
  "get_skype_token_failure_message": "ગ્રાફ API માટે Skype ટોકન મેળવવામાં નિષ્ફળ.",
  "navigation_view_title": "નેવિગેશન",
  "open_contact_card_btn_title": "સંપર્ક કાર્ડ ખોલો",
  "open_contact_card_btn_accessibility_label": "સંપર્ક કાર્ડ બટન ખોલો",
  "start_audio_call_btn_title": "ઑડિયો કૉલ પ્રારંભ કરો",
  "start_audio_call_btn_accessibility_label": "ઑડિયો કૉલ બટન પ્રારંભ કરો",
  "open_chat_btn_title": "ચૅટ ખોલો",
  "open_chat_btn_accessibility_label": "ચૅટ બટન ખોલો",
  "post_message_btn_title": "સંદેશ પોસ્ટ કરો",
  "post_adaptive_card_btn_title": "અનુકૂલનશીલ કાર્ડ પોસ્ટ કરો",
  "post_message_btn_accessibility_label": "સંદેશ પોસ્ટ કરવાનું બટન",
  "open_chat_with_user_mris_btn_title": "ઉપયોગકર્તા સાથે ચૅટ ખોલો",
  "open_chat_with_user_mris_btn_accessibility_label": "ઉપયોગકર્તાબટન સાથે ચૅટ ખોલો",
  "open_meeting_details_btn_title": "મીટિંગની વિગતો ખોલો",
  "open_meeting_details_btn_accessibility_label": "મીટિંગ વિગતોનું બટન ખોલો.",
  "open_view_btn_title": "અન્ય દૃશ્યને ખોલો",
  "open_view_btn_title_with_result": "પરિણામ સાથે અન્ય દૃશ્યને ખોલો",
  "open_view_msg": "હું કોડ માંથી આવું છું!",
  "open_view_deep_link_btn_title": "ડીપ લિંક દ્વારા દૃશ્ય ખોલો",
  "open_view_deep_link_btn_title_with_result": "પરિણામ સાથેના ડીપ લિંક દ્વારા દૃશ્ય ખોલો",
  "open_view_deep_link_msg": "હું એક ઊંડી લિંકમાંથી આવું છું!",
  "open_view_btn_accessibility_label": "અન્ય બટન જુઓને બનાવો",
  "open_view_deep_link_btn_accessibility_label": "ડીપ લિંક બટન દ્વારા અન્ય દૃશ્યને ખોલો",
  "open_modal_btn_title": "મોડલ ખોલો",
  "hide_modal_btn_title": "મોડલ છુપાવો",
  "device_contacts_view_title": "ડિવાઇસ સંપર્કો",
  "get_device_contacts_btn_title": "ડિવાઇસ સંપર્કો મેળવો",
  "get_device_contacts_btn_accessibility_label": "ડિવાઇસ સંપર્કોનું બટન મેળવો",
  "get_device_contacts_result_message": "{contactsCount} સંપર્ક(ર્કો) મળ્યો/મળ્યાં.",
  "get_device_contacts_failure_message": "ડિવાઇસ સંપર્કો મેળવવામાં નિષ્ફળ.",
  "get_device_contacts_permissions_message": "સંપર્કોની અનુમતિ નકારવામાં આવી.",
  "user_avatar_view_title": "વપરાશકર્તા અવતાર",
  "user_avatar_picker_hint": "નામ દ્વારા ઉપયોગકર્તા શોધો",
  "network_connectivity_view_title": "નેટવર્ક કનેક્ટિવિટી",
  "get_network_availability_btn_title": "નેટવર્ક ઉપલબ્ધતા મેળવો",
  "get_network_availability_btn_accessibility_label": "નેટવર્ક ઉપલબ્ધતા બટન મેળવો",
  "get_network_availability_available_message": "નેટવર્ક ઉપલબ્ધ છે",
  "get_network_availability_unavailable_message": "નેટવર્ક અનુપલબ્ધ છે.",
  "get_network_availability_failure_message": "નેટવર્ક ઉપલબ્ધતા મેળવવામાં નિષ્ફળ.",
  "state_layout_view_title": "સ્થિતિ લેઆઉટ",
  "state_layout_error_title": "ભૂલનું શીર્ષક",
  "state_layout_error_desc": "ભૂલનું વર્ણન",
  "state_layout_content": "મુળ વતન પાઠ દૃશ્ય પર પ્રતિક્રિયા",
  "state_layout_loading": "લોડ કરી રહ્યું છે",
  "state_layout_empty": "ખાલી",
  "state_layout_available": "ઉપલબ્ધ",
  "state_layout_error": "ત્રુટી",
  "state_layout_toggle_sync": "ટૉગલ સિંક્રનાઇઝ કરી રહ્યાં છીએ",
  "http_client_view_title": "Http ક્લાયંટ",
  "http_client_get_btn": "કૉલ મેળવોને અમલ કરો",
  "http_client_post_btn": "પોસ્ટ કૉલને અમલ કરો",
  "teams_channels_api": "Teams અને ચૅનલ્સ",
  "tabs_in_chats_api": "ચૅટમાં ટૅબ્સ",
  "waiting": "પ્રતીક્ષા કરી રહ્યું છે...",
  "ok": "ઠીક",
  "fail": "નિષ્ફળ",
  "filter_ok_message": "ફિલ્ટર ઠીક છે.",
  "filter_failed_message": "નિષ્ફળ થયું. અપેક્ષિત 1 હતી પણ {actualCount} teams મળી.",
  "teams_web_view": "Teams વેબ દૃશ્ય",
  "date_time_picker_android": "તારીખસમય પિકર (Android)",
  "date_time_picker_btn": "તારીખસમય પિકર દેખાડો",
  "action_sheets": "ક્રિયા પત્રકો",
  "imageAndFilePicker_view_title": "છબી અને ફાઇલ પિકર",
  "imageAndFilePicker_take_photo_public_store": "ડિફૉલ્ટ કૅમેરા સાથે ફોટો લો અને સાર્વજનિક ફોલ્ડર પર સાચવો",
  "imageAndFilePicker_take_photo_private_store": "ડિફૉલ્ટ કૅમેરા સાથે ફોટો લો અને ખાનગી ફોલ્ડર પર સાચવો",
  "imageAndFilePicker_take_lens_photo_public_store_single_capture": "Office lens સાથે એક ફોટો લો અને સાર્વજનિક ફોલ્ડર પર સાચવો",
  "imageAndFilePicker_take_lens_photo_public_store_single_capture_in_whiteboard": "વ્હાઇટબોર્ડ મોડમાં Office lens સાથે એક ફોટો લો અને સાર્વજનિક ફોલ્ડર પર સાચવો",
  "imageAndFilePicker_take_lens_photo_public_store_multiple_capture": "Office lens સાથે બહુવિધ ફોટા લો અને સાર્વજનિક ફોલ્ડર પર સાચવો",
  "imageAndFilePicker_take_lens_photo_private_store_single_capture": "Office lens સાથે એક ફોટો લો અને ખાનગી ફોલ્ડર પર સાચવો",
  "imageAndFilePicker_take_lens_photo_private_store_multiple_capture": "Office lens સાથે બહુવિધ ફોટા લો અને ખાનગી ફોલ્ડર પર સાચવો",
  "imageAndFilePicker_pick_photo_single_selection": "એકલ પસંદગી સાથે ફોટો ચૂંટો",
  "imageAndFilePicker_pick_photo_multiple_selection": "બહુવિધ પસંદગી સાથે ફોટો ચૂંટો",
  "imageAndFilePicker_pick_document_single_selection": "એકલ પસંદગી સાથે દસ્તાવેજ ચૂંટો",
  "imageAndFilePicker_pick_document_multiple_selection": "બહુવિધ પસંદગી સાથે દસ્તાવેજ ચૂંટો",
  "imageAndFilePicker_capture_image_and_optimise_for_network_upload": "છબીને કૅપ્ચર કરો અને નેટવર્ક અપલોડ માટે અનુકૂલિત કરો",
  "imageAndFilePicker_capture_image_and_compress_quality_excellent": "છબીને કૅપ્ચર કરો અને ઉત્કૃષ્ટ ગુણવત્તાની છબી રૂપે સંકોચિત કરો",
  "imageAndFilePicker_capture_image_and_compress_quality_good": "છબીને કૅપ્ચર કરો અને સારી ગુણવત્તાની છબી રૂપે સંકોચિત કરો",
  "imageAndFilePicker_capture_image_and_compress_quality_moderate": "છબીને કૅપ્ચર કરો અને મધ્યમ ગુણવત્તાની છબી રૂપે સંકોચિત કરો",
  "imageAndFilePicker_capture_image_and_compress_quality_low": "છબીને કૅપ્ચર કરો અને ઓછી ગુણવત્તાની છબી રૂપે સંકોચિત કરો",
  "info": "માહિતી",
  "status": "સ્થિતિ",
  "asyncStorage_view_title": "સ્ટોરેજને અસિંક્રનાઇઝ કરો",
  "fab_layout": "ફેબ લેઆઉટ",
  "filePreview_view_title": "Sharepoint ફાઇલ પૂર્વાવલોકન",
  "show_file_preview_btn_title": "ફાઇલ પૂર્વાવલોકન",
  "show_image_preview_btn_title": "છબી પૂર્વાવલોકન",
  "show_preview_failure_message": "Sharepoint પૂર્વાવલોકન દેખાડવામાં નિષ્ફળ",
  "send_user_bi_event": "BI ઇવેંટ મોકલો",
  "send_scenario_event": "પરિદૃશ્ય ઇવેંટ મોકલો",
  "telemetryClient_title": "ટેલિમેટ્રી ક્લાયંટ",
  "tabbed_component_title": "ટૅબ થયેલ ઘટક",
  "tabbed_component_tab1_title": "ટૅબ1",
  "tabbed_component_tab2_title": "ટૅબ2"
}